core_ai/__init__.py
core_ai/mcp_types.py
core_ai_types-0.2.2.dist-info/METADATA
core_ai_types-0.2.2.dist-info/WHEEL
core_ai_types-0.2.2.dist-info/licenses/LICENSE
core_ai_types-0.2.2.dist-info/RECORD
