Metadata-Version: 2.4
Name: core-ai-types
Version: 0.2.2
Summary: Contains type definitions for CoreAI MCP integration.
Author: Codify AG
License-File: LICENSE
Requires-Python: >=3.12
Requires-Dist: pydantic>=2.11.5
